Tool.py
xytestlib/__init__.py
xytestlib/xylib1.py
xytestlib-1.0.3.dist-info/LICENSE.txt
xytestlib-1.0.3.dist-info/METADATA
xytestlib-1.0.3.dist-info/WHEEL
xytestlib-1.0.3.dist-info/top_level.txt
xytestlib-1.0.3.dist-info/RECORD
