Metadata-Version: 2.1
Name: xytestlib
Version: 1.0.3
Summary: 不打印顶级测试代码
Home-page: https://github.com/wangshunzi/Python_code
Author: Xy
Author-email: 1500671508@qq.com
License: MIT
Platform: UNKNOWN
License-File: LICENSE.txt
